cayley_permutations/__init__.py
cayley_permutations/av.py
cayley_permutations/cayley.py
cayley_permutations-1.0.dist-info/METADATA
cayley_permutations-1.0.dist-info/WHEEL
cayley_permutations-1.0.dist-info/top_level.txt
cayley_permutations-1.0.dist-info/RECORD
